{"filename": "chapter-6.md", "lineno": 57, "status": "unchecked", "code": 0, "uri": "#content-chapter-mesh", "info": ""}
{"filename": "chapter-6.md", "lineno": 57, "status": "unchecked", "code": 0, "uri": "#content-chapter-nodal", "info": ""}
{"filename": "chapter-11.md", "lineno": 194, "status": "unchecked", "code": 0, "uri": "#content-subsubsub-capacitor", "info": ""}
{"filename": "chapter-11.md", "lineno": 341, "status": "unchecked", "code": 0, "uri": "#content-subsubsub-inductor", "info": ""}
{"filename": "chapter-11.md", "lineno": 147, "status": "unchecked", "code": 0, "uri": "#equation-resistors-in-parallel", "info": ""}
{"filename": "chapter-1.md", "lineno": 927, "status": "working", "code": 0, "uri": "https://www.nytimes.com/wirecutter/reviews/best-usb-battery-packs/", "info": ""}
{"filename": "intro.md", "lineno": 32, "status": "unchecked", "code": 0, "uri": "mailto:broderick@ccsu.edu", "info": ""}
{"filename": "intro.md", "lineno": 33, "status": "unchecked", "code": 0, "uri": "mailto:pkootsookos@mxcc.commnet.edu", "info": ""}
{"filename": "chapter-11.md", "lineno": 461, "status": "working", "code": 0, "uri": "https://www.mitre.org/sites/default/files/pdf/06_0667.pdf", "info": ""}
{"filename": "chapter-1.md", "lineno": 927, "status": "working", "code": 0, "uri": "https://www.nist.gov/pml/owm/metric-si/si-units", "info": ""}
{"filename": "chapter-11.md", "lineno": 461, "status": "redirected", "code": 302, "uri": "https://electronics.stackexchange.com/a/68361/4338", "info": "https://electronics.stackexchange.com/questions/68355/inductor-equivalent-of-capacitors-charge/68361#68361"}
{"filename": "chapter-1.md", "lineno": 927, "status": "working", "code": 0, "uri": "https://www.eversource.com/content/residential/account-billing/manage-bill/about-your-bill/rates-tariffs/electric-supply-rates", "info": ""}
